nonebot_plugin_ocgbot_v2/__init__.py
nonebot_plugin_ocgbot_v2/cardPieChart.py
nonebot_plugin_ocgbot_v2/config.py
nonebot_plugin_ocgbot_v2/daily.py
nonebot_plugin_ocgbot_v2/data_update.py
nonebot_plugin_ocgbot_v2/guess_card.py
nonebot_plugin_ocgbot_v2/help.py
nonebot_plugin_ocgbot_v2/libraries/Card.py
nonebot_plugin_ocgbot_v2/libraries/FontUtil.py
nonebot_plugin_ocgbot_v2/libraries/Guess.py
nonebot_plugin_ocgbot_v2/libraries/SqliteUtils.py
nonebot_plugin_ocgbot_v2/libraries/charpic.py
nonebot_plugin_ocgbot_v2/libraries/forbideGet.py
nonebot_plugin_ocgbot_v2/libraries/globalMessage.py
nonebot_plugin_ocgbot_v2/libraries/guessManage.py
nonebot_plugin_ocgbot_v2/libraries/image.py
nonebot_plugin_ocgbot_v2/libraries/raiseCard.py
nonebot_plugin_ocgbot_v2/libraries/randomManage.py
nonebot_plugin_ocgbot_v2/libraries/searchManage.py
nonebot_plugin_ocgbot_v2/libraries/sendAction.py
nonebot_plugin_ocgbot_v2/libraries/staticvar.py
nonebot_plugin_ocgbot_v2/libraries/tool.py
nonebot_plugin_ocgbot_v2/ocg.py
nonebot_plugin_ocgbot_v2/priceSearch.py
nonebot_plugin_ocgbot_v2/static/cdb/cards.cdb
nonebot_plugin_ocgbot_v2/static/cdb/extra_card.cdb
nonebot_plugin_ocgbot_v2/static/cdb/pre-release.cdb
nonebot_plugin_ocgbot_v2/static/decks/deck_list.json
nonebot_plugin_ocgbot_v2/static/fonts/consola.ttf
nonebot_plugin_ocgbot_v2/static/images/background.png
nonebot_plugin_ocgbot_v2/static/images/daily_kapai.png
nonebot_plugin_ocgbot_v2/static/images/daily_xilie.png
nonebot_plugin_ocgbot_v2/static/images/pie_back.png
nonebot_plugin_ocgbot_v2/static/json/daily_card.json
nonebot_plugin_ocgbot_v2/static/json/forbidden.json
nonebot_plugin_ocgbot_v2/static/json/nickname.json
nonebot_plugin_ocgbot_v2/static/pics/114514.jpg
nonebot_plugin_ocgbot_v2/static/pics/114517.jpg
nonebot_plugin_ocgbot_v2/static/pics/所有卡片放置此处.txt
nonebot_plugin_ocgbot_v2-0.2.10.5.dist-info/LICENSE
nonebot_plugin_ocgbot_v2-0.2.10.5.dist-info/METADATA
nonebot_plugin_ocgbot_v2-0.2.10.5.dist-info/WHEEL
nonebot_plugin_ocgbot_v2-0.2.10.5.dist-info/RECORD
