Metadata-Version: 2.3
Name: nonebot-plugin-ocgbot-v2
Version: 0.2.10.5
Summary: nonebot-plugin-ocgbot-v2
License: MIT
Author: fireinsect
Author-email: 847954981@qq.com
Requires-Python: >=3.8.1,<4.0
Classifier: License :: OSI Approved :: MIT License
Classifier: Programming Language :: Python :: 3
Classifier: Programming Language :: Python :: 3.9
Classifier: Programming Language :: Python :: 3.10
Classifier: Programming Language :: Python :: 3.11
Classifier: Programming Language :: Python :: 3.12
Classifier: Programming Language :: Python :: 3.13
Requires-Dist: Pillow (>=9.5.0)
Requires-Dist: httpx (>=0.20.0,<1.0.0)
Requires-Dist: lxml-html-clean (>=0.1.1)
Requires-Dist: matplotlib (>=3.7.1)
Requires-Dist: nonebot-adapter-onebot (>=2.2.3)
Requires-Dist: nonebot2 (>=2.0.0)
Requires-Dist: numpy (>=1.23.0)
Requires-Dist: requests_html (>=0.10.0)
